unitlab/__init__.py
unitlab/__main__.py
unitlab/client.py
unitlab/exceptions.py
unitlab/main.py
unitlab/persistent_tunnel.py
unitlab/utils.py
unitlab-2.3.44.dist-info/licenses/LICENSE.md
unitlab-2.3.44.dist-info/METADATA
unitlab-2.3.44.dist-info/WHEEL
unitlab-2.3.44.dist-info/entry_points.txt
unitlab-2.3.44.dist-info/top_level.txt
unitlab-2.3.44.dist-info/RECORD
