Metadata-Version: 2.4
Name: unitlab
Version: 2.3.44
Home-page: https://github.com/teamunitlab/unitlab-sdk
Author: Unitlab Inc.
Author-email: team@unitlab.ai
License: MIT
Keywords: unitlab-sdk
Classifier: Development Status :: 4 - Beta
Classifier: Intended Audience :: Developers
Classifier: License :: OSI Approved :: MIT License
Classifier: Programming Language :: Python :: 3.9
Classifier: Programming Language :: Python :: 3.10
Classifier: Programming Language :: Python :: 3.11
Classifier: Programming Language :: Python :: 3.12
Classifier: Programming Language :: Python :: 3.13
License-File: LICENSE.md
Requires-Dist: aiohttp
Requires-Dist: aiofiles
Requires-Dist: requests
Requires-Dist: tqdm
Requires-Dist: typer
Requires-Dist: validators
Requires-Dist: psutil
Requires-Dist: pyyaml
Requires-Dist: jupyter
Requires-Dist: python-dotenv
Requires-Dist: uvicorn
Requires-Dist: fastapi
Dynamic: author
Dynamic: author-email
Dynamic: classifier
Dynamic: home-page
Dynamic: keywords
Dynamic: license
Dynamic: license-file
Dynamic: requires-dist
